logbook/__init__.py
logbook/_fallback.py
logbook/_speedups.cpython-313-x86_64-linux-gnu.so
logbook/_termcolors.py
logbook/base.py
logbook/compat.py
logbook/concurrency.py
logbook/handlers.py
logbook/helpers.py
logbook/more.py
logbook/notifiers.py
logbook/queues.py
logbook/ticketing.py
logbook/utils.py
logbook-1.9.1.dist-info/METADATA
logbook-1.9.1.dist-info/WHEEL
logbook-1.9.1.dist-info/top_level.txt
logbook-1.9.1.dist-info/RECORD
logbook-1.9.1.dist-info/licenses/AUTHORS
logbook-1.9.1.dist-info/licenses/LICENSE
